LanKit/__init__.py
LanKit/errors.py
LanKit/Lexer/Lexer.py
LanKit/Lexer/Lexer.pyi
LanKit/Lexer/__init__.py
LanKit/Parser/Parser.py
LanKit/Parser/Parser.pyi
LanKit/Parser/__init__.py
LanKit-0.0.6.dist-info/LICENSE
LanKit-0.0.6.dist-info/METADATA
LanKit-0.0.6.dist-info/WHEEL
LanKit-0.0.6.dist-info/top_level.txt
LanKit-0.0.6.dist-info/RECORD
