Metadata-Version: 2.1
Name: LanKit
Version: 0.0.6
Summary: Internal library of the Immeptor. Needed to create programming languages
Author-email: Markada <markada.py@gmail.com>
License: MIT License
Project-URL: Homepage, https://immeptor.ru
Keywords: Markada,Immeptor,BNF,language,create,parser,lexer
Classifier: Programming Language :: Python :: 3
Classifier: License :: OSI Approved :: MIT License
Classifier: Development Status :: 4 - Beta
Classifier: Natural Language :: Russian
Classifier: Operating System :: OS Independent
Requires-Python: >=3.10
License-File: LICENSE
